{
  "index": 1,
  "domain": "gw/Instances",
  "width": 50,
  "height": 50,
  "boxes": 10,
  "min_size": 2,
  "max_size": 8,
  "actual_boxes": [
    [
      32,
      4,
      36,
      6
    ],
    [
      21,
      41,
      24,
      45
    ],
    [
      7,
      34,
      8,
      36
    ],
    [
      48,
      1,
      49,
      7
    ],
    [
      42,
      3,
      43,
      6
    ],
    [
      37,
      9,
      43,
      12
    ],
    [
      7,
      3,
      9,
      7
    ],
    [
      7,
      44,
      10,
      49
    ],
    [
      20,
      5,
      21,
      7
    ],
    [
      41,
      20,
      44,
      26
    ]
  ],
  "start": [
    23,
    15
  ],
  "goal": [
    16,
    4
  ],
  "ensure_reachability": true,
  "seed": 478163327
}