{
  "index": 2,
  "domain": "gw/Instances",
  "width": 50,
  "height": 50,
  "boxes": 10,
  "min_size": 2,
  "max_size": 8,
  "actual_boxes": [
    [
      35,
      25,
      41,
      27
    ],
    [
      1,
      24,
      3,
      28
    ],
    [
      42,
      23,
      48,
      30
    ],
    [
      36,
      39,
      43,
      44
    ],
    [
      37,
      8,
      40,
      11
    ],
    [
      21,
      6,
      25,
      8
    ],
    [
      23,
      38,
      29,
      39
    ],
    [
      27,
      4,
      33,
      11
    ],
    [
      25,
      31,
      28,
      37
    ],
    [
      7,
      43,
      13,
      48
    ]
  ],
  "start": [
    8,
    30
  ],
  "goal": [
    12,
    50
  ],
  "ensure_reachability": true,
  "seed": 107420369
}